scripts/__init__.py
scripts/cli_splinart.py
splinart/__init__.py
splinart/compute.py
splinart/draw.py
splinart/version.py
splinart/shapes/__init__.py
splinart/shapes/base.py
splinart/spline/__init__.py
splinart/spline/spline.py
splinart/spline/splint.py
splinartpp-0.1.0.dist-info/LICENSE.txt
splinartpp-0.1.0.dist-info/METADATA
splinartpp-0.1.0.dist-info/WHEEL
splinartpp-0.1.0.dist-info/entry_points.txt
splinartpp-0.1.0.dist-info/top_level.txt
splinartpp-0.1.0.dist-info/RECORD
